Metadata-Version: 1.0
Name: write2file
Version: 0.1
Summary: Write content to txt file
Home-page: https://github.com/nofacer/write2file.git
Author: Dustni
Author-email: dustni@qq.com
License: MIT
Platform: UNKNOWN
